{
    "swagger": "2.0",
    "info": {
        "description": "Berikut API-Loyalty Point Agent",
        "title": "API-Loyalty Point Agent",
        "contact": {},
        "version": "1.0"
    },
    "host": "api-dummy.herokuapp.com",
    "basePath": "/",
    "paths": {
        "/v1/login": {
            "post": {
                "description": "Login user",
                "consumes": [
                    "application/json"
                ],
                "produces": [
                    "application/json"
                ],
                "tags": [
                    "User"
                ],
                "summary": "Login",
                "parameters": [
                    {
                        "description": "user",
                        "name": "user",
                        "in": "body",
                        "required": true,
                        "schema": {
                            "$ref": "#/definitions/dummy.AuthLogin"
                        }
                    }
                ],
                "responses": {
                    "200": {
                        "description": "OK",
                        "schema": {
                            "$ref": "#/definitions/dummy.Login"
                        }
                    }
                }
            }
        }
    },
    "definitions": {
        "dummy.AuthLogin": {
            "type": "object",
            "properties": {
                "email": {
                    "type": "string"
                },
                "password": {
                    "type": "string"
                }
            }
        },
        "dummy.Login": {
            "type": "object",
            "properties": {
                "email": {
                    "type": "string"
                },
                "id": {
                    "type": "integer"
                },
                "password": {
                    "type": "string"
                },
                "pin": {
                    "type": "integer"
                },
                "poin": {
                    "type": "integer"
                },
                "token": {
                    "type": "string"
                }
            }
        }
    }
}